README.md
setup.py
partlint/__init__.py
partlint/__main__.py
partlint/database.py
partlint/schematic.py
partlint/si.py
partlint.egg-info/PKG-INFO
partlint.egg-info/SOURCES.txt
partlint.egg-info/dependency_links.txt
partlint.egg-info/entry_points.txt
partlint.egg-info/requires.txt
partlint.egg-info/top_level.txt